{
  "task_id": "module-structure-fix",
  "task_name": "Fix Module Duplication to Eliminate MCP Instance Conflicts",
  "phase": "implementation",
  "started": "2025-11-17T17:30:00Z",
  "updated": "2025-11-17T18:00:00Z",
  "status": "completed",
  "current_step": "all_quality_gates_passed",
  "completed_steps": [
    "read_directive_msg-20251117-173000",
    "created_src_cogito_init_py",
    "updated_pyproject_toml_mypy_config",
    "updated_cogito_main_py_to_fastmcp",
    "passed_mypy_strict_no_found_twice_error",
    "passed_pytest_22_tests",
    "verified_import_cogito_integration",
    "verified_import_top_level_cogito",
    "verified_singleton_mcp_instance",
    "created_PM_021_process_memory",
    "all_quality_gates_passed"
  ],
  "remaining_steps": [],
  "blocked_on": null,
  "questions_for_coordinator": [],
  "artifacts": [
    "src/cogito/__init__.py",
    "pyproject.toml",
    "src/cogito/__main__.py",
    ".bootstrap/process_memory.jsonl",
    ".coordination/outbox/msg-20251117-180000-module-fix-complete.json"
  ],
  "quality_gates": {
    "mypy": {
      "status": "PASSED",
      "mode": "strict",
      "files_checked": 13,
      "errors": 0,
      "critical_fix": "NO MORE 'found twice' ERROR"
    },
    "pytest": {
      "status": "passed",
      "passed": 22,
      "failed": 0,
      "coverage_integration": 53,
      "coverage_overall": 57
    },
    "import_test": {
      "status": "passed",
      "verified_singleton": true
    }
  },
  "root_cause": "Missing src/cogito/__init__.py caused namespace package ambiguity",
  "critical_issue_prevented": "Multiple MCP instances with event loop conflicts",
  "user_contribution": "Pattern recognition from prior experience caught architectural flaw before production",
  "process_memory_entry": "PM-021: Import Hygiene and Module Structure",
  "layer_1_ui_status": "UNBLOCKED - safe to proceed"
}
